{
  "minecraft:adventure/sleep_in_bed": {
    "criteria": {
      "slept_in_bed": "2020-01-27 17:48:32 +0900"
    },
    "done": true
  },
  "minecraft:recipes/transportation/acacia_boat": {
    "criteria": {
      "in_water": "2020-01-27 18:48:57 +0900"
    },
    "done": true
  },
  "minecraft:recipes/transportation/oak_boat": {
    "criteria": {
      "in_water": "2020-01-27 18:48:57 +0900"
    },
    "done": true
  },
  "minecraft:recipes/transportation/dark_oak_boat": {
    "criteria": {
      "in_water": "2020-01-27 18:48:57 +0900"
    },
    "done": true
  },
  "minecraft:recipes/transportation/birch_boat": {
    "criteria": {
      "in_water": "2020-01-27 18:48:57 +0900"
    },
    "done": true
  },
  "minecraft:adventure/root": {
    "criteria": {
      "killed_by_something": "2020-01-27 19:52:16 +0900"
    },
    "done": true
  },
  "minecraft:nether/root": {
    "criteria": {
      "entered_nether": "2020-01-27 21:03:50 +0900"
    },
    "done": true
  },
  "minecraft:recipes/transportation/jungle_boat": {
    "criteria": {
      "in_water": "2020-01-27 18:48:57 +0900"
    },
    "done": true
  },
  "minecraft:recipes/transportation/spruce_boat": {
    "criteria": {
      "in_water": "2020-01-27 18:48:57 +0900"
    },
    "done": true
  },
  "minecraft:story/enter_the_nether": {
    "criteria": {
      "entered_nether": "2020-01-27 21:03:50 +0900"
    },
    "done": true
  },
  "minecraft:adventure/adventuring_time": {
    "criteria": {
      "minecraft:forest": "2020-01-27 18:28:41 +0900",
      "minecraft:mountains": "2020-01-27 18:49:17 +0900",
      "minecraft:badlands_plateau": "2020-01-27 18:59:38 +0900",
      "minecraft:desert_hills": "2020-01-27 18:47:40 +0900",
      "minecraft:desert": "2020-01-27 18:47:31 +0900",
      "minecraft:badlands": "2020-01-27 18:52:27 +0900",
      "minecraft:savanna_plateau": "2020-01-27 17:49:00 +0900",
      "minecraft:dark_forest": "2020-01-27 18:38:43 +0900",
      "minecraft:river": "2020-01-27 17:05:56 +0900",
      "minecraft:wooded_hills": "2020-01-27 18:36:02 +0900",
      "minecraft:wooded_badlands_plateau": "2020-01-27 19:33:42 +0900",
      "minecraft:swamp": "2020-01-27 18:59:21 +0900",
      "minecraft:savanna": "2020-01-27 17:05:57 +0900",
      "minecraft:plains": "2020-01-27 18:28:38 +0900"
    },
    "done": false
  },
  "DataVersion": 2230
}